txtdb/__init__.py
txtdb-1.0.1.dist-info/METADATA
txtdb-1.0.1.dist-info/WHEEL
txtdb-1.0.1.dist-info/top_level.txt
txtdb-1.0.1.dist-info/RECORD
