Metadata-Version: 2.1
Name: txtdb
Version: 1.0.1
Summary: A simple NoSQL database that uses .txt files.
Home-page: UNKNOWN
Author: Marco Vidali
Author-email: <vidali.marco@protonmail.com>
License: UNKNOWN
Keywords: db,database,txt,text,nosql
Platform: UNKNOWN
Classifier: Programming Language :: Python :: 3
Classifier: Operating System :: Unix
Classifier: Operating System :: MacOS :: MacOS X
Classifier: Operating System :: Microsoft :: Windows
